graphitepager/__init__.py
graphitepager/alerts.py
graphitepager/config.py
graphitepager/description.py
graphitepager/graphite_data_record.py
graphitepager/graphite_target.py
graphitepager/level.py
graphitepager/redis_storage.py
graphitepager/utils.py
graphitepager/worker.py
graphitepager/notifiers/__init__.py
graphitepager/notifiers/base.py
graphitepager/notifiers/hipchat_notifier.py
graphitepager/notifiers/notifier_proxy.py
graphitepager/notifiers/pagerduty_notifier.py
graphitepager/notifiers/pushbullet_notifier.py
graphitepager/notifiers/slack_notifier.py
graphitepager/notifiers/stdout_notifier.py
graphitepager-0.2.11.dist-info/DESCRIPTION.rst
graphitepager-0.2.11.dist-info/METADATA
graphitepager-0.2.11.dist-info/RECORD
graphitepager-0.2.11.dist-info/WHEEL
graphitepager-0.2.11.dist-info/entry_points.txt
graphitepager-0.2.11.dist-info/metadata.json
graphitepager-0.2.11.dist-info/top_level.txt
graphitepager-0.2.11.dist-info/zip-safe
