Metadata-Version: 2.0
Name: graphitepager
Version: 0.2.11
Summary: UNKNOWN
Home-page: http://github.com/seatgeek/graphite-pager
Author: Philip Cristiano
Author-email: philipcristiano@gmail.com
License: BSD
Platform: UNKNOWN
Classifier: Intended Audience :: System Administrators
Classifier: License :: OSI Approved :: BSD License
Classifier: Programming Language :: Python :: 2.7
Classifier: Topic :: System :: Monitoring
Requires-Dist: Jinja2 (==2.8)
Requires-Dist: MarkupSafe (==0.23)
Requires-Dist: PyYAML (==3.12)
Requires-Dist: pagerduty (==0.2.1)
Requires-Dist: pushbullet.py (==0.10.0)
Requires-Dist: python-magic (==0.4.12)
Requires-Dist: python-simple-hipchat (==0.4.0)
Requires-Dist: redis (==2.10.5)
Requires-Dist: requests (==2.11.1)
Requires-Dist: six (==1.10.0)
Requires-Dist: websocket-client (==0.37.0)
